Metadata-Version: 2.1
Name: AnteiAPI
Version: 0.0.1.dev5
Summary: AnteiAPI Library
Home-page: UNKNOWN
Author: AnteiCodes
Author-email: anteicodes@gmail.com
License: MIT
Keywords: API,anteicodes
Platform: UNKNOWN
Classifier: Development Status :: 3 - Alpha
Classifier: Intended Audience :: Developers
Classifier: Topic :: Software Development :: Build Tools
Classifier: License :: OSI Approved :: MIT License
Classifier: Programming Language :: Python :: 3.8
Classifier: Programming Language :: Python :: 3.9
